{
    "Certhia brachydactyla": {
        "behaviors": ["song"],
        "translations": {
            "danish": "Korttået træløber",
            "english": "Short-toed treecreeper"
        }
    },
    "Certhia familiaris": {
        "behaviors": ["song"],
        "translations": {
            "danish": "Træløber",
            "english": "Eurasian treecreeper"
        }
    },
    "Cyanistes caeruleus": {
        "behaviors": ["song"],
        "translations": {
            "danish": "Blåmejse",
            "english": "Eurasian blue tit"
        }
    },
    "Erithacus rubecula": {
        "behaviors": ["song"],
        "translations": {
            "danish": "Rødhals",
            "english": "European robin"
        }
    },
    "Fringilla coelebs": {
        "behaviors": ["song"],
        "translations": {
            "danish": "Bogfinke",
            "english": "Common chaffinch"
        }
    },
    "Lophophanes cristatus": {
        "behaviors": ["song"],
        "translations": {
            "danish": "Topmejse",
            "english": "European crested tit"
        }
    },
    "Parus major": {
        "behaviors": ["song"],
        "translations": {
            "danish": "Musvit",
            "english": "Great tit"
        }
    },
    "Periparus ater": {
        "behaviors": ["song"],
        "translations": {
            "danish": "Sortmejse",
            "english": "Coal tit"
        }
    },
    "Phylloscopus collybita": {
        "behaviors": ["song"],
        "translations": {
            "danish": "Gransanger",
            "english": "Common chiffchaff"
        }
    },
    "Phylloscopus trochilus": {
        "behaviors": ["song"],
        "translations": {
            "danish": "Løvsanger",
            "english": "Willow warbler"
        }
    },
    "Poecile palustris": {
        "behaviors": ["song"],
        "translations": {
            "danish": "Sumpmejse",
            "english": "Marsh tit"
        }
    },
    "Regulus regulus": {
        "behaviors": ["song"],
        "translations": {
            "danish": "Fuglekonge",
            "english": "Goldcrest"
        }
    },
    "Sitta europaea": {
        "behaviors": ["song"],
        "translations": {
            "danish": "Spætmejse",
            "english": "Eurasian nuthatch"
        }
    },
    "Troglodytes troglodytes": {
        "behaviors": ["song"],
        "translations": {
            "danish": "Gærdesmutte",
            "english": "Eurasian wren"
        }
    }
}
